{
  "timestamp": "2025-08-11T19:58:12.430Z",
  "config": {
    "cpf": "530.361.406-97",
    "perfil": "Diretor de Secretaria",
    "totalOrgaos": 1
  },
  "results": [
    {
      "orgao": "Vara do Trabalho de Rio Claro",
      "status": "Erro",
      "erro": "(text || \"\").normalize is not a function",
      "timestamp": "2025-08-11T19:58:06.731Z"
    }
  ],
  "summary": {
    "total": 1,
    "sucessos": 0,
    "erros": 1,
    "jaIncluidos": 0,
    "totalValidos": 1,
    "estatisticas": {
      "percentualSucesso": 0,
      "percentualJaExistiam": 0,
      "percentualErros": 100
    }
  },
  "detalhes": {
    "orgaosCadastrados": [],
    "orgaosJaExistiam": [],
    "orgaosComErro": [
      {
        "orgao": "Vara do Trabalho de Rio Claro",
        "erro": "(text || \"\").normalize is not a function"
      }
    ],
    "orgaosPulados": []
  }
}